quant_sdk_lite/__init__.py
quant_sdk_lite/quantsdklite.py
quant_sdk_lite-1.0.4.dist-info/LICENSE
quant_sdk_lite-1.0.4.dist-info/METADATA
quant_sdk_lite-1.0.4.dist-info/WHEEL
quant_sdk_lite-1.0.4.dist-info/top_level.txt
quant_sdk_lite-1.0.4.dist-info/RECORD
