Metadata-Version: 2.1
Name: quant-sdk-lite
Version: 1.0.4
Summary: A python wrapper for Blocksize Capitals Core Api
Home-page: https://github.com/Blocksize-Capital-GmbH/QuantSDK.git
Author: Chris Mintern, Setor Blagogee
Author-email: cm@blocksize-capital.com
License: UNKNOWN
Platform: UNKNOWN
Classifier: Programming Language :: Python :: 3
Classifier: License :: OSI Approved :: GNU General Public License v3 or later (GPLv3+)
Classifier: Operating System :: OS Independent
Requires-Python: >=3.6
Requires-Dist: requests
Requires-Dist: pandas
